trytond/modules/health_nursing/COPYING
trytond/modules/health_nursing/README.rst
trytond/modules/health_nursing/__init__.py
trytond/modules/health_nursing/data/health_nursing_sequences.xml
trytond/modules/health_nursing/data/messages/messages.xml
trytond/modules/health_nursing/exceptions.py
trytond/modules/health_nursing/health.py
trytond/modules/health_nursing/health_nursing.py
trytond/modules/health_nursing/health_nursing_report.xml
trytond/modules/health_nursing/health_nursing_view.xml
trytond/modules/health_nursing/locale/ar.po
trytond/modules/health_nursing/locale/de.po
trytond/modules/health_nursing/locale/el.po
trytond/modules/health_nursing/locale/eo.po
trytond/modules/health_nursing/locale/es.po
trytond/modules/health_nursing/locale/fr.po
trytond/modules/health_nursing/locale/health_nursing.pot
trytond/modules/health_nursing/locale/it_IT.po
trytond/modules/health_nursing/locale/ja_JP.po
trytond/modules/health_nursing/locale/ka.po
trytond/modules/health_nursing/locale/lo.po
trytond/modules/health_nursing/locale/pt_BR.po
trytond/modules/health_nursing/locale/sv.po
trytond/modules/health_nursing/locale/tr.po
trytond/modules/health_nursing/locale/uk.po
trytond/modules/health_nursing/locale/vi.po
trytond/modules/health_nursing/locale/zh_CN.po
trytond/modules/health_nursing/pyproject.toml
trytond/modules/health_nursing/report/ambulatory_care_report.fodt
trytond/modules/health_nursing/security/access_rights.xml
trytond/modules/health_nursing/sequences.py
trytond/modules/health_nursing/tests/__init__.py
trytond/modules/health_nursing/tests/test_health_nursing.py
trytond/modules/health_nursing/tryton.cfg
trytond/modules/health_nursing/view/gnuhealth_ambulatory_care.xml
trytond/modules/health_nursing/view/gnuhealth_ambulatory_procedure_tree.xml
trytond/modules/health_nursing/view/gnuhealth_patient_ambulatory_care.xml
trytond/modules/health_nursing/view/gnuhealth_patient_ambulatory_care_tree.xml
gnuhealth_nursing-5.0.2.dist-info/METADATA
gnuhealth_nursing-5.0.2.dist-info/WHEEL
gnuhealth_nursing-5.0.2.dist-info/licenses/COPYING
gnuhealth_nursing-5.0.2.dist-info/RECORD
